supertuxkart/__init__.py
supertuxkart/account.py
supertuxkart/addons.py
supertuxkart/client.py
supertuxkart/enums.py
supertuxkart/errors.py
supertuxkart/http.py
supertuxkart/ranking.py
supertuxkart/relationships.py
supertuxkart/server.py
supertuxkart/users.py
supertuxkart_py-0.2.2.dist-info/licenses/LICENSE
supertuxkart_py-0.2.2.dist-info/METADATA
supertuxkart_py-0.2.2.dist-info/WHEEL
supertuxkart_py-0.2.2.dist-info/top_level.txt
supertuxkart_py-0.2.2.dist-info/RECORD
