Metadata-Version: 2.4
Name: supertuxkart.py
Version: 0.2.2
Summary: A wrapper for the SuperTuxKart Online Service (STKAddons) API
Author-email: Vyxie <kitakita@disroot.org>
License-Expression: MIT
Project-URL: Homepage, https://codeberg.org/linaSTK/stk.py
Project-URL: Issues, https://codeberg.org/linaSTK/stk.py/issues
Classifier: Programming Language :: Python :: 3
Classifier: Operating System :: OS Independent
Requires-Python: >=3.10
License-File: LICENSE
Requires-Dist: requests
Requires-Dist: aiohttp
Dynamic: license-file
